{
  "title": "The Results of My Author/Classmate Discovering My Yuri Obsession!",
  "description": "What happens when a classmate finds out about another girl's secret yuri obsession/feelings? A yuri comedy ensues! Author's twitter: https://twitter.com/pluto_305",
  "artist": "pluto_305",
  "author": "pluto_305",
  "cover": "https://i.imgur.com/bJWk1uf.jpg",
  "chapters": { 
    "1": {
      "title": "Two Seconds After Meeting",
      "volume": "1",
      "groups": {
        "Asian-Scanlation-Sensation": "/proxy/api/imgur/chapter/1ATKWoj/"
      },
      "last_updated": "1617736187"
    },  
    "2": {
      "title": "The Art of Suspense",
      "volume": "1",
      "groups": {
        "Asian-Scanlation-Sensation": "/proxy/api/imgur/chapter/FYP0nLz/"
      },
      "last_updated": "1617736187"
    },  
    "3": {
      "title": "Too Much Information",
      "volume": "1",
      "groups": {
        "Asian-Scanlation-Sensation": "/proxy/api/imgur/chapter/XkOGNTd/"
      },
      "last_updated": "1617736187"
    },  
    "4": {
      "title": "A Hurdle Taller than Mt. Fuji",
      "volume": "1",
      "groups": {
        "Asian-Scanlation-Sensation": "/proxy/api/imgur/chapter/67ezTYX/"
      },
      "last_updated": "1617736187"
    },  
    "5": {
      "title": "Unique Circumstances",
      "volume": "1",
      "groups": {
        "Asian-Scanlation-Sensation": "/proxy/api/imgur/chapter/CuEHdYA/"
      },
      "last_updated": "1617736187"
    },  
    "6": {
      "title": "Straightening Things Out",
      "volume": "1",
      "groups": {
        "Asian-Scanlation-Sensation": "/proxy/api/imgur/chapter/UzshSij/"
      },
      "last_updated": "1617736187"
    },  
    "7": {
      "title": "Analysis Deeper than the Mariana Trench",
      "volume": "1",
      "groups": {
        "Asian-Scanlation-Sensation": "/proxy/api/imgur/chapter/syFQ24p/"
      },
      "last_updated": "1617736187"
    },  
    "8": {
      "title": "I Guarantee It",
      "volume": "1",
      "groups": {
        "Asian-Scanlation-Sensation": "/proxy/api/imgur/chapter/DDFpWnX/"
      },
      "last_updated": "1617736187"
    },  
    "9": {
      "title": "The Type to Wet Their Pillow",
      "volume": "1",
      "groups": {
        "Asian-Scanlation-Sensation": "/proxy/api/imgur/chapter/Oms6bEA/"
      },
      "last_updated": "1617736187"
    },  
    "10": {
      "title": "The Power of Being an Author",
      "volume": "1",
      "groups": {
        "Asian-Scanlation-Sensation": "/proxy/api/imgur/chapter/aTnwryf/"
      },
      "last_updated": "1617736187"
    },  
    "11": {
      "title": "She Did it Right Away",
      "volume": "1",
      "groups": {
        "Asian-Scanlation-Sensation": "/proxy/api/imgur/chapter/DpDZbcM/"
      },
      "last_updated": "1617736187"
    },  
    "12": {
      "title": "Breathless",
      "volume": "1",
      "groups": {
        "Asian-Scanlation-Sensation": "/proxy/api/imgur/chapter/c00W0Ay/"
      },
      "last_updated": "1617736187"
    },  
    "13": {
      "title": "A Narrow-Minded Perspective",
      "volume": "1",
      "groups": {
        "Asian-Scanlation-Sensation": "/proxy/api/imgur/chapter/70ODzGF/"
      },
      "last_updated": "1617736187"
    },  
    "14": {
      "title": "It Just Doesn't Make Any Sense",
      "volume": "1",
      "groups": {
        "Asian-Scanlation-Sensation": "/proxy/api/imgur/chapter/yPLckfB/"
      },
      "last_updated": "1617736187"
    },  
    "15": {
      "title": "Passionate Pigeonholing",
      "volume": "1",
      "groups": {
        "Asian-Scanlation-Sensation": "/proxy/api/imgur/chapter/fQy9Svy/"
      },
      "last_updated": "1617736187"
    },  
    "16": {
      "title": "The Witness",
      "volume": "1",
      "groups": {
        "Asian-Scanlation-Sensation": "/proxy/api/imgur/chapter/ggypAmD/"
      },
      "last_updated": "1617736187"
    },
    "17": {
      "title": "I Don't Even Know Anymore...",
      "volume": "1",
      "groups": {
        "Asian-Scanlation-Sensation": "/proxy/api/imgur/chapter/JEqHjIt/"
      },
      "last_updated": "1617736187"
    },
    "18": {
      "title": "Perfect Counter",
      "volume": "1",
      "groups": {
        "Asian-Scanlation-Sensation": "/proxy/api/imgur/chapter/jfsx8xA/"
      },
      "last_updated": "1617736187"
    },
    "19": {
      "title": "A Huge Flag",
      "volume": "1",
      "groups": {
        "Asian-Scanlation-Sensation": "/proxy/api/imgur/chapter/gpMbh5X/"
      },
      "last_updated": "1617736187"
    },
    "20": {
      "title": "Physically",
      "volume": "1",
      "groups": {
        "Asian-Scanlation-Sensation": "/proxy/api/imgur/chapter/u6oXMwk/"
      },
      "last_updated": "1617736187"
    },
    "21": {
      "title": "Forced to Hear More",
      "volume": "1",
      "groups": {
        "Asian-Scanlation-Sensation": "/proxy/api/imgur/chapter/SJkBiXl/"
      },
      "last_updated": "1617736187"
    },
    "22": {
      "title": "First Time Seeing Such a Shameless Otaku",
      "volume": "1",
      "groups": {
        "Asian-Scanlation-Sensation": "/proxy/api/imgur/chapter/97GxOnN/"
      },
      "last_updated": "1617736187"
    },
    "23": {
      "title": "It Started Long Ago...",
      "volume": "1",
      "groups": {
        "Asian-Scanlation-Sensation": "/proxy/api/imgur/chapter/ZHCrFjB/"
      },
      "last_updated": "1617736187"
    },
    "24": {
      "title": "The Girl Named Julie Saonji",
      "volume": "1",
      "groups": {
        "Asian-Scanlation-Sensation": "/proxy/api/imgur/chapter/JF8BI0E/"
      },
      "last_updated": "1617736187"
    },
    "25": {
      "title": "The Girl Named Hiromi Tachibana",
      "volume": "1",
      "groups": {
        "Asian-Scanlation-Sensation": "/proxy/api/imgur/chapter/OZXkNbR/"
      },
      "last_updated": "1617736187"
    },
    "26": {
      "title": "The Girl Named Julie Saonji 2",
      "volume": "1",
      "groups": {
        "Asian-Scanlation-Sensation": "/proxy/api/imgur/chapter/R10gC4p/"
      },
      "last_updated": "1617736187"
    },
    "27": {
      "title": "Secrets Are Like Eyelashes",
      "volume": "1",
      "groups": {
        "Asian-Scanlation-Sensation": "/proxy/api/imgur/chapter/5HGBYHF/"
      },
      "last_updated": "1617736187"
    },
    "28": {
      "title": "This Lifestyle is #1!",
      "volume": "1",
      "groups": {
        "Asian-Scanlation-Sensation": "/proxy/api/imgur/chapter/ojI3YQh/"
      },
      "last_updated": "1617736187"
    },
    "29": {
      "title": "Emotional Instability",
      "volume": "1",
      "groups": {
        "Asian-Scanlation-Sensation": "/proxy/api/imgur/chapter/PzJw4Mn/"
      },
      "last_updated": "1617736187"
    },
    "30": {
      "title": "An Author's Thought Process",
      "volume": "1",
      "groups": {
        "Asian-Scanlation-Sensation": "/proxy/api/imgur/chapter/fYJI3z0/"
      },
      "last_updated": "1617736187"
    },
    "31": {
      "title": "Studying Methods",
      "volume": "1",
      "groups": {
        "Asian-Scanlation-Sensation": "/proxy/api/imgur/chapter/fHodN0K/"
      },
      "last_updated": "1617736187"
    }
  }
}
